{
  "_description": "Site knowledge base for HaxJobs auto-apply. Each platform has known selectors, field patterns, and quirks. Updated as we reverse-engineer more platforms.",
  "_version": "1.0.0",
  "_updated": "2026-06-07",
  
  "lever": {
    "name": "Lever",
    "url_patterns": ["jobs.lever.co"],
    "api": {
      "jobs": "https://api.lever.co/v0/postings/{company}?mode=json",
      "apply_endpoint": "https://jobs.lever.co/v1/apply/{company}/{job_id}",
      "notes": "REST API for job listings. Apply endpoint accepts multipart form POST."
    },
    "form_selectors": {
      "full_name": "input[name='name'], input[id*='name'], input[placeholder*='name']",
      "email": "input[name='email'], input[type='email']",
      "phone": "input[name='phone'], input[type='tel']",
      "location": "input[name='location'], input[id*='location'], select[name='opportunityLocationId']",
      "linkedin": "input[name='urls[LinkedIn]'], input[name*='linkedin'], input[placeholder*='LinkedIn']",
      "github": "input[name='urls[GitHub]'], input[name*='github'], input[placeholder*='GitHub']",
      "portfolio": "input[name='urls[Portfolio]'], input[name*='portfolio']",
      "current_company": "input[name='org'], input[name*='company'], input[placeholder*='company']",
      "resume_upload": "input[type='file']",
      "cover_letter": "textarea[name*='cover'], textarea[id*='cover'], textarea[placeholder*='cover'], textarea[placeholder*='Write here']",
      "submit": "button[type='submit'], button:has-text('Submit'), button:has-text('Apply')"
    },
    "quirks": {
      "file_upload": "Supports PDF, DOC, DOCX. Max 5MB typically.",
      "submit_behavior": "Single-page form, no CAPTCHA on standard applications.",
      "auto_fill_risk": "LOW — Lever is the most automation-friendly ATS.",
      "known_issues": "Some companies add custom questions (work authorization, visa). Must pause before these.",
      "cookie_consent": false,
      "rate_limiting": "None observed for application submissions."
    },
    "confidence": "high"
  },

  "greenhouse": {
    "name": "Greenhouse",
    "url_patterns": ["boards.greenhouse.io", "greenhouse.io"],
    "api": {
      "jobs": "https://boards.greenhouse.io/{company} (HTML parse)",
      "apply_endpoint": "POST to /{company}/jobs/{job_id}/applications",
      "notes": "No public JSON API for jobs. Form submit is standard multipart POST."
    },
    "form_selectors": {
      "full_name": "input[name='job_application[first_name]'], input[name='job_application[last_name]']",
      "email": "input[name='job_application[email]']",
      "phone": "input[name='job_application[phone]']",
      "location": "input[name='job_application[location]']",
      "linkedin": "input[name*='linkedin'], input[name*='urls[LinkedIn]']",
      "github": "input[name*='github'], input[name*='urls[GitHub]']",
      "resume_upload": "input[name='job_application[resume]'], input[type='file']",
      "cover_letter": "textarea[name='job_application[cover_letter]']",
      "submit": "button[type='submit'], input[type='submit'], button:has-text('Submit')"
    },
    "quirks": {
      "file_upload": "PDF, DOC, DOCX, TXT. Resume required field.",
      "submit_behavior": "Multi-page form — Greenhouse splits into sections (Personal Info, Resume, Questions, Demographics). Demographics always optional.",
      "auto_fill_risk": "LOW-MEDIUM — multi-page means more steps, but all selectors are consistent.",
      "known_issues": "Demographics page at the end — always skip. Some companies use Greenhouse's 'custom questions' feature heavily.",
      "cookie_consent": false,
      "rate_limiting": "None observed."
    },
    "confidence": "high"
  },

  "ashby": {
    "name": "Ashby",
    "url_patterns": ["jobs.ashbyhq.com", "ashbyhq.com"],
    "api": {
      "jobs": "https://api.ashbyhq.com/posting-api/job-board/{company}",
      "apply_endpoint": "POST to form action URL (dynamic per job)",
      "notes": "JSON API for job listings. Form is standard HTML POST, no CAPTCHA."
    },
    "form_selectors": {
      "full_name": "input[name='name'], input[name='full_name'], input[id*='name']",
      "email": "input[name='email'], input[type='email']",
      "phone": "input[name='phone'], input[type='tel']",
      "resume_upload": "input[type='file']",
      "cover_letter": "textarea[name*='cover'], textarea[placeholder*='cover']",
      "linkedin": "input[name*='linkedin'], input[placeholder*='LinkedIn']",
      "submit": "button[type='submit'], button:has-text('Submit')"
    },
    "quirks": {
      "file_upload": "PDF preferred. Resume required.",
      "submit_behavior": "Single-page or two-page form. Clean, consistent HTML.",
      "auto_fill_risk": "LOW — Ashby is simple and consistent.",
      "known_issues": "Rarely has custom questions. Usually just resume + basics.",
      "cookie_consent": false,
      "rate_limiting": "None observed."
    },
    "confidence": "medium"
  },

  "workday": {
    "name": "Workday",
    "url_patterns": ["myworkdayjobs.com", "workday.com"],
    "api": {
      "jobs": "HTML parse only (heavy SPA, SSR content)",
      "apply_endpoint": "POST to dynamic endpoint (per company subdomain)",
      "notes": "Heavy JavaScript SPA. Each company has unique subdomain and form structure. Hardest ATS to automate."
    },
    "form_selectors": {
      "full_name": "input[data-automation-id='name'], input[id*='name']",
      "email": "input[data-automation-id='email'], input[type='email']",
      "phone": "input[data-automation-id='phone'], input[type='tel']",
      "resume_upload": "input[type='file'], button[data-automation-id='upload']",
      "submit": "button[data-automation-id='submit']"
    },
    "quirks": {
      "file_upload": "Supports PDF, DOC, DOCX.",
      "submit_behavior": "Multi-step wizard. Can be 5-10 pages. Each company customizes heavily.",
      "auto_fill_risk": "HIGH — each Workday instance is customized. Selectors change per company. Not recommended for auto-apply.",
      "known_issues": "CAPTCHA sometimes. Requires manual session for login. Cookie consent wall.",
      "cookie_consent": true,
      "rate_limiting": "None observed, but heavy JS makes automation fragile.",
      "recommendation": "Manual apply only. Use Playwright to pre-fill fields, but always require human approval before submit."
    },
    "confidence": "low"
  },

  "smartrecruiters": {
    "name": "SmartRecruiters",
    "url_patterns": ["smartrecruiters.com", "jobs.smartrecruiters.com"],
    "api": {
      "jobs": "HTML parse",
      "apply_endpoint": "POST to form action",
      "notes": "Modern ATS, clean HTML. Less common than Lever/Greenhouse but growing."
    },
    "form_selectors": {
      "full_name": "input[name='firstname'], input[name='lastname']",
      "email": "input[name='email'], input[type='email']",
      "phone": "input[name='phonenumber'], input[type='tel']",
      "resume_upload": "input[type='file']",
      "submit": "button[type='submit'], button:has-text('Apply')"
    },
    "quirks": {
      "file_upload": "PDF, DOC, DOCX.",
      "submit_behavior": "Single-page form, clean and consistent.",
      "auto_fill_risk": "LOW-MEDIUM — relatively simple, but less tested than Lever/Greenhouse.",
      "cookie_consent": false,
      "rate_limiting": "None observed."
    },
    "confidence": "low"
  },

  "workable": {
    "name": "Workable",
    "url_patterns": ["apply.workable.com", "workable.com"],
    "api": {
      "jobs": "HTML parse",
      "apply_endpoint": "POST to /{company}/j/{job_id}/apply",
      "notes": "Clean, modern ATS. Single-page forms. No CAPTCHA."
    },
    "form_selectors": {
      "full_name": "input[name='name'], input[name='fullname']",
      "email": "input[name='email'], input[type='email']",
      "phone": "input[name='phone'], input[type='tel']",
      "resume_upload": "input[type='file']",
      "cover_letter": "textarea[name='cover_letter'], textarea[name='message']",
      "submit": "button[type='submit'], button:has-text('Submit')"
    },
    "quirks": {
      "file_upload": "PDF, DOC, DOCX.",
      "submit_behavior": "Clean single-page form. One of the easier ATS platforms.",
      "auto_fill_risk": "LOW — Workable is automation-friendly.",
      "cookie_consent": false,
      "rate_limiting": "None observed."
    },
    "confidence": "low"
  }
}
